[
  {
    "direction": "Flat", 
    "trend": 4, 
    "dateString": "2016-09-11T06:08:04.000Z", 
    "sgv": 141, 
    "device": "share2", 
    "date": 1473574084000, 
    "_id": "57d4f53a29678dc19bfb87af", 
    "type": "sgv", 
    "glucose": 141
  }, 
  {
    "direction": "Flat", 
    "trend": 4, 
    "dateString": "2016-09-11T06:03:03.000Z", 
    "sgv": 144, 
    "device": "share2", 
    "date": 1473573783000, 
    "_id": "57d4f40e29678dc19bfb87ab", 
    "type": "sgv", 
    "glucose": 144
  }, 
  {
    "direction": "FortyFiveDown", 
    "trend": 5, 
    "dateString": "2016-09-11T05:58:04.000Z", 
    "sgv": 147, 
    "device": "share2", 
    "date": 1473573484000, 
    "_id": "57d4f2e229678dc19bfb87a7", 
    "type": "sgv", 
    "glucose": 147
  }, 
  {
    "direction": "FortyFiveDown", 
    "trend": 5, 
    "dateString": "2016-09-11T05:48:02.000Z", 
    "sgv": 156, 
    "device": "share2", 
    "date": 1473572882000, 
    "_id": "57d4f08a29678dc19bfb87a0", 
    "type": "sgv", 
    "glucose": 156
  }, 
  {
    "direction": "Flat", 
    "trend": 4, 
    "dateString": "2016-09-11T05:43:06.000Z", 
    "sgv": 161, 
    "device": "share2", 
    "date": 1473572586000, 
    "_id": "57d4ef5e29678dc19bfb879c", 
    "type": "sgv", 
    "glucose": 161
  }, 
  {
    "direction": "Flat", 
    "trend": 4, 
    "dateString": "2016-09-11T05:38:03.000Z", 
    "sgv": 167, 
    "device": "share2", 
    "date": 1473572283000, 
    "_id": "57d4ee3229678dc19bfb8798", 
    "type": "sgv", 
    "glucose": 167
  }, 
  {
    "direction": "Flat", 
    "trend": 4, 
    "dateString": "2016-09-11T05:33:06.000Z", 
    "sgv": 172, 
    "device": "share2", 
    "date": 1473571986000, 
    "_id": "57d4ed0629678dc19bfb8794", 
    "type": "sgv", 
    "glucose": 172
  }, 
  {
    "direction": "Flat", 
    "trend": 4, 
    "dateString": "2016-09-11T05:28:08.000Z", 
    "sgv": 174, 
    "device": "share2", 
    "date": 1473571688000, 
    "_id": "57d4ebda29678dc19bfb8790", 
    "type": "sgv", 
    "glucose": 174
  }, 
  {
    "direction": "Flat", 
    "trend": 4, 
    "dateString": "2016-09-11T05:23:04.000Z", 
    "sgv": 173, 
    "device": "share2", 
    "date": 1473571384000, 
    "_id": "57d4eaae29678dc19bfb878c", 
    "type": "sgv", 
    "glucose": 173
  }, 
  {
    "direction": "FortyFiveUp", 
    "trend": 3, 
    "dateString": "2016-09-11T05:18:02.000Z", 
    "sgv": 172, 
    "device": "share2", 
    "date": 1473571082000, 
    "_id": "57d4e98229678dc19bfb8788", 
    "type": "sgv", 
    "glucose": 172
  }
]