[
  {
    "direction": "Flat", 
    "trend": 4, 
    "dateString": "2016-06-30T20:11:27.000Z", 
    "sgv": 116, 
    "device": "share2", 
    "date": 1467317487000, 
    "_id": "57757d1229678dc19bf904bf", 
    "type": "sgv", 
    "glucose": 116
  }, 
  {
    "direction": "Flat", 
    "trend": 4, 
    "dateString": "2016-06-30T20:06:27.000Z", 
    "sgv": 116, 
    "device": "share2", 
    "date": 1467317187000, 
    "_id": "57757be529678dc19bf904bb", 
    "type": "sgv", 
    "glucose": 116
  }, 
  {
    "direction": "Flat", 
    "trend": 4, 
    "dateString": "2016-06-30T20:01:26.000Z", 
    "sgv": 121, 
    "device": "share2", 
    "date": 1467316886000, 
    "_id": "57757ab929678dc19bf904b7", 
    "type": "sgv", 
    "glucose": 121
  }, 
  {
    "direction": "Flat", 
    "trend": 4, 
    "dateString": "2016-06-30T19:56:27.000Z", 
    "sgv": 126, 
    "device": "share2", 
    "date": 1467316587000, 
    "_id": "5775798d29678dc19bf904b2", 
    "type": "sgv", 
    "glucose": 126
  }, 
  {
    "direction": "Flat", 
    "trend": 4, 
    "dateString": "2016-06-30T19:51:27.000Z", 
    "sgv": 123, 
    "device": "share2", 
    "date": 1467316287000, 
    "_id": "5775786129678dc19bf904ae", 
    "type": "sgv", 
    "glucose": 123
  }, 
  {
    "direction": "Flat", 
    "trend": 4, 
    "dateString": "2016-06-30T19:41:26.000Z", 
    "sgv": 118, 
    "device": "share2", 
    "date": 1467315686000, 
    "_id": "5775760929678dc19bf904a6", 
    "type": "sgv", 
    "glucose": 118
  }, 
  {
    "direction": "Flat", 
    "trend": 4, 
    "dateString": "2016-06-30T19:36:26.000Z", 
    "sgv": 117, 
    "device": "share2", 
    "date": 1467315386000, 
    "_id": "577574dd29678dc19bf904a0", 
    "type": "sgv", 
    "glucose": 117
  }, 
  {
    "direction": "Flat", 
    "trend": 4, 
    "dateString": "2016-06-30T19:31:28.000Z", 
    "sgv": 124, 
    "device": "share2", 
    "date": 1467315088000, 
    "_id": "577573b129678dc19bf90498", 
    "type": "sgv", 
    "glucose": 124
  }, 
  {
    "direction": "Flat", 
    "trend": 4, 
    "dateString": "2016-06-30T19:26:28.000Z", 
    "sgv": 129, 
    "device": "share2", 
    "date": 1467314788000, 
    "_id": "5775728529678dc19bf90492", 
    "type": "sgv", 
    "glucose": 129
  }, 
  {
    "direction": "Flat", 
    "trend": 4, 
    "dateString": "2016-06-30T19:21:27.000Z", 
    "sgv": 129, 
    "device": "share2", 
    "date": 1467314487000, 
    "_id": "5775715929678dc19bf9048c", 
    "type": "sgv", 
    "glucose": 129
  }
]