[
  {
    "direction": "Flat", 
    "trend": 4, 
    "dateString": "2016-09-04T10:28:17.000Z", 
    "sgv": 154, 
    "device": "share2", 
    "date": 1472984897000, 
    "_id": "57cbf77129678dc19bfb4d14", 
    "type": "sgv", 
    "glucose": 154
  }, 
  {
    "direction": "Flat", 
    "trend": 4, 
    "dateString": "2016-09-04T10:23:18.000Z", 
    "sgv": 154, 
    "device": "share2", 
    "date": 1472984598000, 
    "_id": "57cbf64529678dc19bfb4d0e", 
    "type": "sgv", 
    "glucose": 154
  }, 
  {
    "direction": "Flat", 
    "trend": 4, 
    "dateString": "2016-09-04T10:18:19.000Z", 
    "sgv": 153, 
    "device": "share2", 
    "date": 1472984299000, 
    "_id": "57cbf51929678dc19bfb4d08", 
    "type": "sgv", 
    "glucose": 153
  }, 
  {
    "direction": "Flat", 
    "trend": 4, 
    "dateString": "2016-09-04T10:13:17.000Z", 
    "sgv": 152, 
    "device": "share2", 
    "date": 1472983997000, 
    "_id": "57cbf3ed29678dc19bfb4d01", 
    "type": "sgv", 
    "glucose": 152
  }, 
  {
    "direction": "Flat", 
    "trend": 4, 
    "dateString": "2016-09-04T10:08:17.000Z", 
    "sgv": 153, 
    "device": "share2", 
    "date": 1472983697000, 
    "_id": "57cbf2c129678dc19bfb4cfc", 
    "type": "sgv", 
    "glucose": 153
  }, 
  {
    "direction": "Flat", 
    "trend": 4, 
    "dateString": "2016-09-04T10:03:17.000Z", 
    "sgv": 154, 
    "device": "share2", 
    "date": 1472983397000, 
    "_id": "57cbf19529678dc19bfb4cf7", 
    "type": "sgv", 
    "glucose": 154
  }, 
  {
    "direction": "Flat", 
    "trend": 4, 
    "dateString": "2016-09-04T09:58:17.000Z", 
    "sgv": 154, 
    "device": "share2", 
    "date": 1472983097000, 
    "_id": "57cbf06929678dc19bfb4cf1", 
    "type": "sgv", 
    "glucose": 154
  }, 
  {
    "direction": "Flat", 
    "trend": 4, 
    "dateString": "2016-09-04T09:53:20.000Z", 
    "sgv": 154, 
    "device": "share2", 
    "date": 1472982800000, 
    "_id": "57cbef3d29678dc19bfb4ced", 
    "type": "sgv", 
    "glucose": 154
  }, 
  {
    "direction": "Flat", 
    "trend": 4, 
    "dateString": "2016-09-04T09:48:17.000Z", 
    "sgv": 151, 
    "device": "share2", 
    "date": 1472982497000, 
    "_id": "57cbee1129678dc19bfb4ce8", 
    "type": "sgv", 
    "glucose": 151
  }, 
  {
    "direction": "Flat", 
    "trend": 4, 
    "dateString": "2016-09-04T09:43:30.000Z", 
    "sgv": 147, 
    "device": "share2", 
    "date": 1472982210000, 
    "_id": "57cbece529678dc19bfb4ce3", 
    "type": "sgv", 
    "glucose": 147
  }
]