[
  {
    "direction": "Flat", 
    "trend": 4, 
    "dateString": "2016-06-24T04:26:58.000Z", 
    "sgv": 182, 
    "device": "share2", 
    "date": 1466742418000, 
    "_id": "576cb6ba29678dc19bf8cf41", 
    "type": "sgv", 
    "glucose": 182
  }, 
  {
    "direction": "Flat", 
    "trend": 4, 
    "dateString": "2016-06-24T04:21:46.000Z", 
    "sgv": 193, 
    "device": "share2", 
    "date": 1466742106000, 
    "_id": "576cb58e29678dc19bf8cf3e", 
    "type": "sgv", 
    "glucose": 193
  }, 
  {
    "direction": "FortyFiveUp", 
    "trend": 3, 
    "dateString": "2016-06-24T04:16:44.000Z", 
    "sgv": 199, 
    "device": "share2", 
    "date": 1466741804000, 
    "_id": "576cb46229678dc19bf8cf3a", 
    "type": "sgv", 
    "glucose": 199
  }, 
  {
    "direction": "FortyFiveUp", 
    "trend": 3, 
    "dateString": "2016-06-24T04:11:45.000Z", 
    "sgv": 196, 
    "device": "share2", 
    "date": 1466741505000, 
    "_id": "576cb33629678dc19bf8cf38", 
    "type": "sgv", 
    "glucose": 196
  }, 
  {
    "direction": "Flat", 
    "trend": 4, 
    "dateString": "2016-06-24T03:56:45.000Z", 
    "sgv": 179, 
    "device": "share2", 
    "date": 1466740605000, 
    "_id": "576cafb229678dc19bf8cf2d", 
    "type": "sgv", 
    "glucose": 179
  }, 
  {
    "direction": "Flat", 
    "trend": 4, 
    "dateString": "2016-06-24T03:51:44.000Z", 
    "sgv": 176, 
    "device": "share2", 
    "date": 1466740304000, 
    "_id": "576cae8629678dc19bf8cf2a", 
    "type": "sgv", 
    "glucose": 176
  }, 
  {
    "direction": "FortyFiveUp", 
    "trend": 3, 
    "dateString": "2016-06-24T03:46:42.000Z", 
    "sgv": 170, 
    "device": "share2", 
    "date": 1466740002000, 
    "_id": "576cad5a29678dc19bf8cf26", 
    "type": "sgv", 
    "glucose": 170
  }, 
  {
    "direction": "FortyFiveUp", 
    "trend": 3, 
    "dateString": "2016-06-24T03:41:45.000Z", 
    "sgv": 167, 
    "device": "share2", 
    "date": 1466739705000, 
    "_id": "576cac2e29678dc19bf8cf20", 
    "type": "sgv", 
    "glucose": 167
  }, 
  {
    "direction": "FortyFiveUp", 
    "trend": 3, 
    "dateString": "2016-06-24T03:36:47.000Z", 
    "sgv": 167, 
    "device": "share2", 
    "date": 1466739407000, 
    "_id": "576cab0229678dc19bf8cf1c", 
    "type": "sgv", 
    "glucose": 167
  }, 
  {
    "direction": "Flat", 
    "trend": 4, 
    "dateString": "2016-06-24T03:31:44.000Z", 
    "sgv": 154, 
    "device": "share2", 
    "date": 1466739104000, 
    "_id": "576ca9d629678dc19bf8cf18", 
    "type": "sgv", 
    "glucose": 154
  }
]