[
  {
    "direction": "Flat", 
    "trend": 4, 
    "dateString": "2016-07-06T01:41:13.000Z", 
    "sgv": 82, 
    "device": "share2", 
    "date": 1467769273000, 
    "_id": "577c623329678dc19bf93241", 
    "type": "sgv", 
    "glucose": 82
  }, 
  {
    "direction": "Flat", 
    "trend": 4, 
    "dateString": "2016-07-06T01:26:15.000Z", 
    "sgv": 79, 
    "device": "share2", 
    "date": 1467768375000, 
    "_id": "577c5eaf29678dc19bf93234", 
    "type": "sgv", 
    "glucose": 79
  }, 
  {
    "direction": "Flat", 
    "trend": 4, 
    "dateString": "2016-07-06T01:21:15.000Z", 
    "sgv": 79, 
    "device": "share2", 
    "date": 1467768075000, 
    "_id": "577c5d8229678dc19bf9322c", 
    "type": "sgv", 
    "glucose": 79
  }, 
  {
    "direction": "Flat", 
    "trend": 4, 
    "dateString": "2016-07-06T01:16:14.000Z", 
    "sgv": 79, 
    "device": "share2", 
    "date": 1467767774000, 
    "_id": "577c5c5629678dc19bf93223", 
    "type": "sgv", 
    "glucose": 79
  }, 
  {
    "direction": "Flat", 
    "trend": 4, 
    "dateString": "2016-07-06T01:06:14.000Z", 
    "sgv": 78, 
    "device": "share2", 
    "date": 1467767174000, 
    "_id": "577c59fe29678dc19bf9321c", 
    "type": "sgv", 
    "glucose": 78
  }, 
  {
    "direction": "Flat", 
    "trend": 4, 
    "dateString": "2016-07-06T01:01:13.000Z", 
    "sgv": 80, 
    "device": "share2", 
    "date": 1467766873000, 
    "_id": "577c58d229678dc19bf93217", 
    "type": "sgv", 
    "glucose": 80
  }, 
  {
    "direction": "Flat", 
    "trend": 4, 
    "dateString": "2016-07-06T00:56:17.000Z", 
    "sgv": 81, 
    "device": "share2", 
    "date": 1467766577000, 
    "_id": "577c57a629678dc19bf93214", 
    "type": "sgv", 
    "glucose": 81
  }, 
  {
    "direction": "Flat", 
    "trend": 4, 
    "dateString": "2016-07-06T00:46:14.000Z", 
    "sgv": 78, 
    "device": "share2", 
    "date": 1467765974000, 
    "_id": "577c554e29678dc19bf9320a", 
    "type": "sgv", 
    "glucose": 78
  }, 
  {
    "direction": "Flat", 
    "trend": 4, 
    "dateString": "2016-07-06T00:41:19.000Z", 
    "sgv": 79, 
    "device": "share2", 
    "date": 1467765679000, 
    "_id": "577c542229678dc19bf93206", 
    "type": "sgv", 
    "glucose": 79
  }, 
  {
    "direction": "Flat", 
    "trend": 4, 
    "dateString": "2016-07-06T00:36:15.000Z", 
    "sgv": 82, 
    "device": "share2", 
    "date": 1467765375000, 
    "_id": "577c52f629678dc19bf93200", 
    "type": "sgv", 
    "glucose": 82
  }
]