[
  {
    "direction": "Flat", 
    "trend": 4, 
    "dateString": "2016-07-26T15:00:22.000Z", 
    "sgv": 145, 
    "device": "share2", 
    "date": 1469545222000, 
    "_id": "57977b2f29678dc19bf9d9c7", 
    "type": "sgv", 
    "glucose": 145
  }, 
  {
    "direction": "Flat", 
    "trend": 4, 
    "dateString": "2016-07-26T14:55:22.000Z", 
    "sgv": 141, 
    "device": "share2", 
    "date": 1469544922000, 
    "_id": "57977a0229678dc19bf9d9c2", 
    "type": "sgv", 
    "glucose": 141
  }, 
  {
    "direction": "Flat", 
    "trend": 4, 
    "dateString": "2016-07-26T14:50:21.000Z", 
    "sgv": 135, 
    "device": "share2", 
    "date": 1469544621000, 
    "_id": "579778d629678dc19bf9d9bd", 
    "type": "sgv", 
    "glucose": 135
  }, 
  {
    "direction": "Flat", 
    "trend": 4, 
    "dateString": "2016-07-26T14:45:22.000Z", 
    "sgv": 131, 
    "device": "share2", 
    "date": 1469544322000, 
    "_id": "579777aa29678dc19bf9d9b7", 
    "type": "sgv", 
    "glucose": 131
  }, 
  {
    "direction": "Flat", 
    "trend": 4, 
    "dateString": "2016-07-26T14:40:22.000Z", 
    "sgv": 130, 
    "device": "share2", 
    "date": 1469544022000, 
    "_id": "5797767e29678dc19bf9d9b2", 
    "type": "sgv", 
    "glucose": 130
  }, 
  {
    "direction": "Flat", 
    "trend": 4, 
    "dateString": "2016-07-26T14:35:22.000Z", 
    "sgv": 128, 
    "device": "share2", 
    "date": 1469543722000, 
    "_id": "5797755229678dc19bf9d9ab", 
    "type": "sgv", 
    "glucose": 128
  }, 
  {
    "direction": "Flat", 
    "trend": 4, 
    "dateString": "2016-07-26T14:30:24.000Z", 
    "sgv": 126, 
    "device": "share2", 
    "date": 1469543424000, 
    "_id": "5797742629678dc19bf9d9a5", 
    "type": "sgv", 
    "glucose": 126
  }, 
  {
    "direction": "Flat", 
    "trend": 4, 
    "dateString": "2016-07-26T14:25:23.000Z", 
    "sgv": 125, 
    "device": "share2", 
    "date": 1469543123000, 
    "_id": "579772fa29678dc19bf9d99f", 
    "type": "sgv", 
    "glucose": 125
  }, 
  {
    "direction": "Flat", 
    "trend": 4, 
    "dateString": "2016-07-26T14:20:23.000Z", 
    "sgv": 123, 
    "device": "share2", 
    "date": 1469542823000, 
    "_id": "579771ce29678dc19bf9d99a", 
    "type": "sgv", 
    "glucose": 123
  }, 
  {
    "direction": "Flat", 
    "trend": 4, 
    "dateString": "2016-07-26T14:15:30.000Z", 
    "sgv": 117, 
    "device": "share2", 
    "date": 1469542530000, 
    "_id": "579770a229678dc19bf9d994", 
    "type": "sgv", 
    "glucose": 117
  }
]