[
  {
    "direction": "SingleUp", 
    "trend": 2, 
    "dateString": "2016-08-22T02:09:19.000Z", 
    "sgv": 120, 
    "device": "share2", 
    "date": 1471831759000, 
    "_id": "57ba5ef529678dc19bfad576", 
    "type": "sgv", 
    "glucose": 120
  }, 
  {
    "direction": "FortyFiveUp", 
    "trend": 3, 
    "dateString": "2016-08-22T02:04:25.000Z", 
    "sgv": 107, 
    "device": "share2", 
    "date": 1471831465000, 
    "_id": "57ba5dc929678dc19bfad56f", 
    "type": "sgv", 
    "glucose": 107
  }, 
  {
    "direction": "Flat", 
    "trend": 4, 
    "dateString": "2016-08-22T01:59:17.000Z", 
    "sgv": 93, 
    "device": "share2", 
    "date": 1471831157000, 
    "_id": "57ba5c9d29678dc19bfad56a", 
    "type": "sgv", 
    "glucose": 93
  }, 
  {
    "direction": "Flat", 
    "trend": 4, 
    "dateString": "2016-08-22T01:54:32.000Z", 
    "sgv": 87, 
    "device": "share2", 
    "date": 1471830872000, 
    "_id": "57ba5b7129678dc19bfad563", 
    "type": "sgv", 
    "glucose": 87
  }, 
  {
    "direction": "Flat", 
    "trend": 4, 
    "dateString": "2016-08-22T01:49:20.000Z", 
    "sgv": 87, 
    "device": "share2", 
    "date": 1471830560000, 
    "_id": "57ba5a4529678dc19bfad55d", 
    "type": "sgv", 
    "glucose": 87
  }, 
  {
    "direction": "Flat", 
    "trend": 4, 
    "dateString": "2016-08-22T01:39:18.000Z", 
    "sgv": 89, 
    "device": "share2", 
    "date": 1471829958000, 
    "_id": "57ba57ed29678dc19bfad54e", 
    "type": "sgv", 
    "glucose": 89
  }, 
  {
    "direction": "Flat", 
    "trend": 4, 
    "dateString": "2016-08-22T01:34:21.000Z", 
    "sgv": 87, 
    "device": "share2", 
    "date": 1471829661000, 
    "_id": "57ba56c129678dc19bfad548", 
    "type": "sgv", 
    "glucose": 87
  }, 
  {
    "direction": "Flat", 
    "trend": 4, 
    "dateString": "2016-08-22T01:29:16.000Z", 
    "sgv": 89, 
    "device": "share2", 
    "date": 1471829356000, 
    "_id": "57ba559529678dc19bfad541", 
    "type": "sgv", 
    "glucose": 89
  }, 
  {
    "direction": "Flat", 
    "trend": 4, 
    "dateString": "2016-08-22T01:24:18.000Z", 
    "sgv": 90, 
    "device": "share2", 
    "date": 1471829058000, 
    "_id": "57ba546929678dc19bfad533", 
    "type": "sgv", 
    "glucose": 90
  }, 
  {
    "direction": "Flat", 
    "trend": 4, 
    "dateString": "2016-08-22T01:19:20.000Z", 
    "sgv": 90, 
    "device": "share2", 
    "date": 1471828760000, 
    "_id": "57ba533c29678dc19bfad52e", 
    "type": "sgv", 
    "glucose": 90
  }
]