[
  {
    "direction": "Flat", 
    "trend": 4, 
    "dateString": "2016-08-02T01:05:06.000Z", 
    "sgv": 55, 
    "device": "share2", 
    "date": 1470099906000, 
    "_id": "579ff1c929678dc19bfa1134", 
    "type": "sgv", 
    "glucose": 55
  }, 
  {
    "direction": "Flat", 
    "trend": 4, 
    "dateString": "2016-08-02T01:00:06.000Z", 
    "sgv": 55, 
    "device": "share2", 
    "date": 1470099606000, 
    "_id": "579ff09d29678dc19bfa112e", 
    "type": "sgv", 
    "glucose": 55
  }, 
  {
    "direction": "Flat", 
    "trend": 4, 
    "dateString": "2016-08-02T00:55:06.000Z", 
    "sgv": 55, 
    "device": "share2", 
    "date": 1470099306000, 
    "_id": "579fef7129678dc19bfa1128", 
    "type": "sgv", 
    "glucose": 55
  }, 
  {
    "direction": "Flat", 
    "trend": 4, 
    "dateString": "2016-08-02T00:50:10.000Z", 
    "sgv": 57, 
    "device": "share2", 
    "date": 1470099010000, 
    "_id": "579feedb29678dc19bfa1127", 
    "type": "sgv", 
    "glucose": 57
  }, 
  {
    "direction": "Flat", 
    "trend": 4, 
    "dateString": "2016-08-02T00:45:09.000Z", 
    "sgv": 58, 
    "device": "share2", 
    "date": 1470098709000, 
    "_id": "579fed1929678dc19bfa111c", 
    "type": "sgv", 
    "glucose": 58
  }, 
  {
    "direction": "Flat", 
    "trend": 4, 
    "dateString": "2016-08-02T00:40:07.000Z", 
    "sgv": 60, 
    "device": "share2", 
    "date": 1470098407000, 
    "_id": "579febed29678dc19bfa1117", 
    "type": "sgv", 
    "glucose": 60
  }, 
  {
    "direction": "Flat", 
    "trend": 4, 
    "dateString": "2016-08-02T00:35:06.000Z", 
    "sgv": 62, 
    "device": "share2", 
    "date": 1470098106000, 
    "_id": "579feac129678dc19bfa1111", 
    "type": "sgv", 
    "glucose": 62
  }, 
  {
    "direction": "FortyFiveDown", 
    "trend": 5, 
    "dateString": "2016-08-02T00:30:06.000Z", 
    "sgv": 63, 
    "device": "share2", 
    "date": 1470097806000, 
    "_id": "579fe99529678dc19bfa110a", 
    "type": "sgv", 
    "glucose": 63
  }, 
  {
    "direction": "FortyFiveDown", 
    "trend": 5, 
    "dateString": "2016-08-02T00:25:06.000Z", 
    "sgv": 68, 
    "device": "share2", 
    "date": 1470097506000, 
    "_id": "579fe86929678dc19bfa1104", 
    "type": "sgv", 
    "glucose": 68
  }, 
  {
    "direction": "FortyFiveDown", 
    "trend": 5, 
    "dateString": "2016-08-02T00:20:07.000Z", 
    "sgv": 74, 
    "device": "share2", 
    "date": 1470097207000, 
    "_id": "579fe73d29678dc19bfa10ff", 
    "type": "sgv", 
    "glucose": 74
  }
]