[
  {
    "direction": "FortyFiveUp", 
    "trend": 3, 
    "dateString": "2016-09-05T15:38:15.000Z", 
    "sgv": 111, 
    "device": "share2", 
    "date": 1473089895000, 
    "_id": "57cd91a029678dc19bfb5876", 
    "type": "sgv", 
    "glucose": 111
  }, 
  {
    "direction": "Flat", 
    "trend": 4, 
    "dateString": "2016-09-05T15:28:19.000Z", 
    "sgv": 96, 
    "device": "share2", 
    "date": 1473089299000, 
    "_id": "57cd8f4829678dc19bfb586c", 
    "type": "sgv", 
    "glucose": 96
  }, 
  {
    "direction": "Flat", 
    "trend": 4, 
    "dateString": "2016-09-05T15:23:14.000Z", 
    "sgv": 95, 
    "device": "share2", 
    "date": 1473088994000, 
    "_id": "57cd8e1c29678dc19bfb5867", 
    "type": "sgv", 
    "glucose": 95
  }, 
  {
    "direction": "Flat", 
    "trend": 4, 
    "dateString": "2016-09-05T15:18:14.000Z", 
    "sgv": 95, 
    "device": "share2", 
    "date": 1473088694000, 
    "_id": "57cd8cf129678dc19bfb5861", 
    "type": "sgv", 
    "glucose": 95
  }, 
  {
    "direction": "Flat", 
    "trend": 4, 
    "dateString": "2016-09-05T15:03:14.000Z", 
    "sgv": 89, 
    "device": "share2", 
    "date": 1473087794000, 
    "_id": "57cd896c29678dc19bfb5856", 
    "type": "sgv", 
    "glucose": 89
  }, 
  {
    "direction": "Flat", 
    "trend": 4, 
    "dateString": "2016-09-05T14:58:14.000Z", 
    "sgv": 88, 
    "device": "share2", 
    "date": 1473087494000, 
    "_id": "57cd884029678dc19bfb5850", 
    "type": "sgv", 
    "glucose": 88
  }, 
  {
    "direction": "Flat", 
    "trend": 4, 
    "dateString": "2016-09-05T14:48:27.000Z", 
    "sgv": 88, 
    "device": "share2", 
    "date": 1473086907000, 
    "_id": "57cd85e829678dc19bfb5844", 
    "type": "sgv", 
    "glucose": 88
  }, 
  {
    "direction": "Flat", 
    "trend": 4, 
    "dateString": "2016-09-05T14:43:14.000Z", 
    "sgv": 89, 
    "device": "share2", 
    "date": 1473086594000, 
    "_id": "57cd84bc29678dc19bfb583e", 
    "type": "sgv", 
    "glucose": 89
  }, 
  {
    "direction": "Flat", 
    "trend": 4, 
    "dateString": "2016-09-05T14:38:15.000Z", 
    "sgv": 89, 
    "device": "share2", 
    "date": 1473086295000, 
    "_id": "57cd839029678dc19bfb5837", 
    "type": "sgv", 
    "glucose": 89
  }, 
  {
    "direction": "Flat", 
    "trend": 4, 
    "dateString": "2016-09-05T14:33:21.000Z", 
    "sgv": 89, 
    "device": "share2", 
    "date": 1473086001000, 
    "_id": "57cd826429678dc19bfb5833", 
    "type": "sgv", 
    "glucose": 89
  }
]