{
  "device": "openaps://raspberrypi", 
  "pump": {
    "battery": {
      "status": "normal", 
      "voltage": 1.42
    }, 
    "status": {
      "status": "normal", 
      "timestamp": "2016-08-02T07:53:02.000Z", 
      "bolusing": false, 
      "suspended": false
    }, 
    "reservoir": 63.6, 
    "clock": "2016-08-02T00:52:44-07:00"
  }, 
  "openaps": {
    "suggested": {
      "bg": 128, 
      "temp": "absolute", 
      "snoozeBG": 103, 
      "timestamp": "2016-08-02T07:52:56.000Z", 
      "reason": "Eventual BG 103 > 100 but Avg. Delta -2.00 < Exp. Delta -0.9, temp 0.85 ~ req 0.85U/hr", 
      "eventualBG": 103, 
      "mealAssist": "Off: Carbs: undefined Boluses: undefined ISF: 40, Target: 100 Deviation: 1 BGI: -0.78", 
      "tick": -2
    }, 
    "iob": {
      "netbasalinsulin": 0.75, 
      "timestamp": "2016-08-02T07:52:52.000Z", 
      "activity": 0.0039, 
      "basaliob": 0.66, 
      "hightempinsulin": 0.75, 
      "bolussnooze": 0, 
      "iob": 0.66
    }
  }
}