{
  "device": "openaps://raspberrypi", 
  "pump": {
    "battery": {
      "status": "normal", 
      "voltage": 1.21
    }, 
    "status": {
      "status": "normal", 
      "timestamp": "2016-07-11T07:49:00.000Z", 
      "bolusing": false, 
      "suspended": false
    }, 
    "reservoir": 156.05, 
    "clock": "2016-07-11T00:48:29-07:00"
  }, 
  "openaps": {
    "suggested": {
      "bg": 143, 
      "temp": "absolute", 
      "snoozeBG": 109, 
      "timestamp": "2016-07-11T07:48:51.000Z", 
      "rate": 1.15, 
      "reason": "Eventual BG 109 >= 100, 23m@0.950 = 0.364 > req 0.14+0.1U. Setting temp basal of 0.85U/hr", 
      "eventualBG": 109, 
      "duration": 30, 
      "mealAssist": "Off: Carbs: undefined Boluses: undefined ISF: 40, Target: 100 Deviation: 4 BGI: -2.42", 
      "tick": -1
    }, 
    "iob": {
      "netbasalinsulin": 2.3, 
      "timestamp": "2016-07-11T07:48:48.000Z", 
      "activity": 0.0121, 
      "basaliob": 0.955, 
      "hightempinsulin": 2.3, 
      "bolussnooze": 0, 
      "iob": 0.955
    }
  }
}