{
  "device": "openaps://raspberrypi", 
  "pump": {
    "battery": {
      "status": "normal", 
      "voltage": 1.4
    }, 
    "status": {
      "status": "normal", 
      "timestamp": "2016-08-02T09:09:04.000Z", 
      "bolusing": false, 
      "suspended": false
    }, 
    "reservoir": 62.525, 
    "clock": "2016-08-02T02:08:46-07:00"
  }, 
  "openaps": {
    "suggested": {
      "bg": 110, 
      "temp": "absolute", 
      "snoozeBG": 94, 
      "timestamp": "2016-08-02T09:08:57.000Z", 
      "rate": 0.25, 
      "reason": "Eventual BG 94 < 100, setting 0.25U/hr", 
      "eventualBG": 94, 
      "duration": 30, 
      "mealAssist": "Off: Carbs: undefined Boluses: undefined ISF: 40, Target: 100 Deviation: -8 BGI: -1.04", 
      "tick": -3
    }, 
    "iob": {
      "netbasalinsulin": 0.75, 
      "timestamp": "2016-08-02T09:08:53.000Z", 
      "activity": 0.0052, 
      "basaliob": 0.198, 
      "hightempinsulin": 0.8, 
      "bolussnooze": 0, 
      "iob": 0.198
    }
  }
}